mpris_client_asyncio/__init__.py
mpris_client_asyncio-1.0.2.dist-info/LICENSE
mpris_client_asyncio-1.0.2.dist-info/METADATA
mpris_client_asyncio-1.0.2.dist-info/WHEEL
mpris_client_asyncio-1.0.2.dist-info/top_level.txt
mpris_client_asyncio-1.0.2.dist-info/RECORD
