Metadata-Version: 2.1
Name: mpris-client-asyncio
Version: 1.0.2
Summary: Client library for MPRIS that uses asyncio
Home-page: https://github.com/yashBhosale/mpris-client-asyncio
Author: Yash Bhosale
Author-email: bhosaley5@gmail.com
License: UNKNOWN
Project-URL: Bug Tracker, https://github.com/yashBhosale/mpris-client-asyncio/issues
Platform: UNKNOWN
Classifier: Operating System :: POSIX :: Linux
Classifier: License :: OSI Approved :: MIT License
Classifier: Framework :: AsyncIO
Requires-Python: >=3.6
Requires-Dist: dbussy
